[{"id":"Dye_10","slug":"lovely-dye","name":"Lovely Dye","icon":"dye_10_demonhunter_male","path":"item/lovely-dye-Dye_10"},{"id":"Dye_01","slug":"tanners-dye","name":"Tanner's Dye","icon":"dye_01_demonhunter_male","path":"item/tanners-dye-Dye_01"},{"id":"Dye_20","slug":"abyssal-dye","name":"Abyssal Dye","icon":"dye_20_demonhunter_male","path":"item/abyssal-dye-Dye_20"},{"id":"Dye_16","slug":"golden-dye","name":"Golden Dye","icon":"dye_16_demonhunter_male","path":"item/golden-dye-Dye_16"},{"id":"Dye_08","slug":"desert-dye","name":"Desert Dye","icon":"dye_08_demonhunter_male","path":"item/desert-dye-Dye_08"},{"id":"Dye_04","slug":"aquatic-dye","name":"Aquatic Dye","icon":"dye_04_demonhunter_male","path":"item/aquatic-dye-Dye_04"},{"id":"Dye_13","slug":"elegant-dye","name":"Elegant Dye","icon":"dye_13_demonhunter_male","path":"item/elegant-dye-Dye_13"},{"id":"Dye_09","slug":"autumn-dye","name":"Autumn Dye","icon":"dye_09_demonhunter_male","path":"item/autumn-dye-Dye_09"},{"id":"Dye_11","slug":"summer-dye","name":"Summer Dye","icon":"dye_11_demonhunter_male","path":"item/summer-dye-Dye_11"},{"id":"Dye_12","slug":"spring-dye","name":"Spring Dye","icon":"dye_12_demonhunter_male","path":"item/spring-dye-Dye_12"},{"id":"Dye_CE_02","slug":"bottled-smoke","name":"Bottled Smoke","icon":"dye_ce_02_demonhunter_male","path":"item/bottled-smoke-Dye_CE_02"},{"id":"Dye_05","slug":"cardinal-dye","name":"Cardinal Dye","icon":"dye_05_demonhunter_male","path":"item/cardinal-dye-Dye_05"},{"id":"Dye_06","slug":"rangers-dye","name":"Ranger's Dye","icon":"dye_06_demonhunter_male","path":"item/rangers-dye-Dye_06"},{"id":"Dye_CE_01","slug":"bottled-cloud","name":"Bottled Cloud","icon":"dye_ce_01_demonhunter_male","path":"item/bottled-cloud-Dye_CE_01"},{"id":"Dye_15","slug":"mariners-dye","name":"Mariner's Dye","icon":"dye_15_demonhunter_male","path":"item/mariners-dye-Dye_15"},{"id":"Dye_Vanishing","slug":"vanishing-dye","name":"Vanishing Dye","icon":"dye_vanishing_demonhunter_male","path":"item/vanishing-dye-Dye_Vanishing"},{"id":"Dye_14","slug":"foresters-dye","name":"Forester's Dye","icon":"dye_14_demonhunter_male","path":"item/foresters-dye-Dye_14"},{"id":"Dye_Remover","slug":"allsoaps-miraculous-dye-remover","name":"All-Soap's Miraculous Dye Remover","icon":"dye_remover_demonhunter_male","path":"item/allsoaps-miraculous-dye-remover-Dye_Remover"},{"id":"Dye_18","slug":"infernal-dye","name":"Infernal Dye","icon":"dye_18_demonhunter_male","path":"item/infernal-dye-Dye_18"},{"id":"Dye_03","slug":"winter-dye","name":"Winter Dye","icon":"dye_03_demonhunter_male","path":"item/winter-dye-Dye_03"},{"id":"Dye_19","slug":"purity-dye","name":"Purity Dye","icon":"dye_19_demonhunter_male","path":"item/purity-dye-Dye_19"},{"id":"Dye_17","slug":"royal-dye","name":"Royal Dye","icon":"dye_17_demonhunter_male","path":"item/royal-dye-Dye_17"}]