{"id":"Unique_Gloves_009_1xx","slug":"ashearas-iron-fist","name":"Asheara's Iron Fist","icon":"unique_gloves_009_1xx_demonhunter_male","tooltipParams":"/artisan/blacksmith/recipe/ashearas-iron-fist","requiredLevel":52,"stackSizeMax":0,"accountBound":true,"flavorText":"These gloves represent the unspoken bond between Asheara and her mercenaries.","flavorTextHtml":"<span class=\"d3-color-ffc7b377\">These gloves represent the unspoken bond between Asheara and her mercenaries.</span>","typeName":"Set Gloves","type":{"twoHanded":false,"id":"Gloves"},"armor":"169 - 191","armorHtml":"169 - 191","color":"green","isSeasonRequiredToDrop":false,"seasonRequiredToDrop":-1,"slots":["hands"],"attributes":{"primary":[{"textHtml":"<span class=\"tooltip-icon-bullet\"></span> <span class=\"d3-color-ff6969ff\">+[270 - 299] Strength</span>","text":"+[270 - 299] Strength"}],"secondary":[{"textHtml":"<span class=\"tooltip-icon-bullet\"></span> <span class=\"d3-color-ff6969ff\">+[61 - 80] Arcane Resistance</span>","text":"+[61 - 80] Arcane Resistance"},{"textHtml":"<span class=\"tooltip-icon-utility\"></span> <span class=\"d3-color-ff6969ff\">[13 - 20]% Better Chance of Finding Magical Items</span>","text":"[13 - 20]% Better Chance of Finding Magical Items"}],"other":[]},"setName":"Asheara's Uniform","setNameHtml":"<p><span class=\"d3-color-ff00ff00\">Asheara's Uniform</span></p>","setDescription":"(2) Set:     \n +30 Resistance to All Elements(3) Set:     \n 2.50% of Damage Dealt Is Converted to Life    \n +300 Holy Thorns Damage","setDescriptionHtml":"<span class=\"d3-color-ff00ff00\">(2) Set: <br />    <span class=\"tooltip-icon-bullet\"></span> +30 Resistance to All Elements</span><br /><span class=\"d3-color-ff00ff00\">(3) Set: <br />    <span class=\"tooltip-icon-bullet\"></span> 2.50% of Damage Dealt Is Converted to Life<br />    <span class=\"tooltip-icon-bullet\"></span> +300 Holy Thorns Damage</span><br />","setItems":["item/ashearas-gait-Unique_Pants_009_1xx","item/ashearas-tracks-Unique_Boots_014_1xx","item/ashearas-guard-Unique_Shoulder_017_1xx"]}