{"id":"P2_HealthPotionLegendary_07","slug":"bottomless-potion-of-rejuvenation","name":"Bottomless Potion of Rejuvenation","icon":"p2_healthpotionlegendary_07_demonhunter_male","tooltipParams":"/item/bottomless-potion-of-rejuvenation-P2_HealthPotionLegendary_07","requiredLevel":61,"stackSizeMax":0,"accountBound":true,"flavorText":"\"When you are losing a fight, healing is no help, as you'll just lose that health in turn. No, what you need is a potion that gives you energy. And I know how to make that potion!\" -Prisoner Jentulf, in a letter to the King pleading for early release.","flavorTextHtml":"<span class=\"d3-color-ffc7b377\">\"When you are losing a fight, healing is no help, as you'll just lose that health in turn. No, what you need is a potion that gives you energy. And I know how to make that potion!\" -Prisoner Jentulf, in a letter to the King pleading for early release.</span>","typeName":"Legendary Potion","type":{"twoHanded":false,"id":"HealthPotion"},"color":"orange","description":"Instantly restores 60% Life.","descriptionHtml":"<p>Instantly restores <span class=\"d3-color-green\">60%</span> Life.</p>","isSeasonRequiredToDrop":false,"seasonRequiredToDrop":-1,"slots":[],"attributes":{"primary":[],"secondary":[{"textHtml":"<span class=\"d3-color-ffff8000\"><span class=\"tooltip-icon-utility\"></span> Restores <span class=\"d3-color-magic\">20%</span> resource when used below 50% health.</span> <span class=\"d3-color-ff9b9b9b\">[20 - 30]%</span>","text":"Restores 20% resource when used below 50% health. [20 - 30]%"}],"other":[]},"setItems":[]}