{"id":"CraftingPlan_Jeweler_GemCombine_x1_Emerald_09_10","slug":"design-flawless-royal-emerald","name":"Design: Flawless Royal Emerald","icon":"craftingplan_jeweler_gemcombine_x1_emerald_09_10_demonhunter_male","tooltipParams":"/item/design-flawless-royal-emerald-CraftingPlan_Jeweler_GemCombine_x1_Emerald_09_10","requiredLevel":0,"stackSizeMax":10,"accountBound":false,"typeName":"Rare Jeweler Design","type":{"twoHanded":false,"id":"CraftingPlan_Jeweler"},"color":"yellow","description":"Teaches the Jeweler how to combine three Royal Emerald into one Flawless Royal Emerald.","descriptionHtml":"<p>Teaches the Jeweler how to combine three Royal Emerald into one Flawless Royal Emerald.</p>","isSeasonRequiredToDrop":false,"seasonRequiredToDrop":-1,"slots":[],"setItems":[]}