{"id":"CraftingPlan_Smith_T11_Amulet_Str","slug":"design-amulet-of-strength","name":"Design: Amulet of Strength","icon":"craftingplan_smith_t11_amulet_str_demonhunter_male","tooltipParams":"/item/design-amulet-of-strength-CraftingPlan_Smith_T11_Amulet_Str","requiredLevel":0,"stackSizeMax":10,"accountBound":false,"typeName":"Rare Jeweler Design","type":{"twoHanded":false,"id":"CraftingPlan_Jeweler"},"color":"yellow","description":"Teaches the Jeweler how to craft an Amulet with Strength and 5 random properties.","descriptionHtml":"<p>Teaches the Jeweler how to craft an Amulet with Strength and 5 random properties.</p>","isSeasonRequiredToDrop":false,"seasonRequiredToDrop":-1,"slots":[],"setItems":[]}