{"id":"Unique_Amulet_105_x1","slug":"golden-gorget-of-leoric","name":"Golden Gorget of Leoric","icon":"unique_amulet_105_x1_demonhunter_male","tooltipParams":"/item/golden-gorget-of-leoric-Unique_Amulet_105_x1","requiredLevel":15,"stackSizeMax":0,"accountBound":true,"flavorText":"Despite the powerful enchantments upon it, this ornate piece of armor nonetheless failed to stop noble Lachdanan from ending the life of the Mad King.","flavorTextHtml":"<span class=\"d3-color-ffc7b377\">Despite the powerful enchantments upon it, this ornate piece of armor nonetheless failed to stop noble Lachdanan from ending the life of the Mad King.</span>","typeName":"Legendary Amulet","type":{"twoHanded":false,"id":"Amulet"},"color":"orange","isSeasonRequiredToDrop":false,"seasonRequiredToDrop":-1,"slots":["neck","follower-neck"],"attributes":{"primary":[{"textHtml":"<span class=\"tooltip-icon-bullet\"></span> <span class=\"d3-color-ff6969ff\">Critical Hit Chance Increased by [8.0 - 10.0]%</span>","text":"Critical Hit Chance Increased by [8.0 - 10.0]%"},{"textHtml":"<span class=\"tooltip-icon-bullet\"></span> <span class=\"d3-color-ff6969ff\">+[91 - 100] Resistance to All Elements</span>","text":"+[91 - 100] Resistance to All Elements"}],"secondary":[{"textHtml":"<span class=\"d3-color-ffff8000\"> After earning a massacre bonus, <span class=\"d3-color-magic\">6</span> Skeletons are summoned to fight by your side for 10 seconds.</span> <span class=\"d3-color-ff9b9b9b\">[4 - 6]</span>","text":"After earning a massacre bonus, 6 Skeletons are summoned to fight by your side for 10 seconds. [4 - 6]"}],"other":[]},"randomAffixes":[{"oneOf":[{"textHtml":"<span class=\"tooltip-icon-bullet\"></span> <span class=\"d3-color-ff6969ff\">+[626 - 750] Strength</span>","text":"+[626 - 750] Strength"},{"textHtml":"<span class=\"tooltip-icon-bullet\"></span> <span class=\"d3-color-ff6969ff\">+[626 - 750] Dexterity</span>","text":"+[626 - 750] Dexterity"},{"textHtml":"<span class=\"tooltip-icon-bullet\"></span> <span class=\"d3-color-ff6969ff\">+[626 - 750] Intelligence</span>","text":"+[626 - 750] Intelligence"}]}],"setItems":[]}