{"id":"P69_Unique_Amulet_02","slug":"haunted-visions","name":"Haunted Visions","icon":"p69_unique_amulet_02_demonhunter_male","tooltipParams":"/item/haunted-visions-P69_Unique_Amulet_02","requiredLevel":70,"stackSizeMax":0,"accountBound":true,"flavorText":"The spirits of the dead are never far. Search for them only a little, and they shall appear.","flavorTextHtml":"<span class=\"d3-color-ffc7b377\">The spirits of the dead are never far. Search for them only a little, and they shall appear.</span>","typeName":"Legendary Amulet","type":{"twoHanded":false,"id":"Amulet"},"color":"orange","isSeasonRequiredToDrop":false,"seasonRequiredToDrop":-1,"slots":["neck","follower-neck"],"attributes":{"primary":[],"secondary":[{"textHtml":"<span class=\"tooltip-icon-utility\"></span> <span class=\"d3-color-ff6969ff\">Sockets (1)</span>","text":"Sockets (1)"},{"textHtml":"<span class=\"d3-color-ffff8000\"> Simulacrum now drains 1% of your maximum life every second and lasts forever. They can now duplicate Grim Scythe instead of Skeletal Mage.</span> <span class=\"d3-color-ffff0000\">(Necromancer Only)</span> <span class=\"d3-color-ff9b9b9b\">1%</span>","text":"Simulacrum now drains 1% of your maximum life every second and lasts forever. They can now duplicate Grim Scythe instead of Skeletal Mage. (Necromancer Only) 1%"}],"other":[]},"randomAffixes":[{"oneOf":[{"textHtml":"<span class=\"tooltip-icon-bullet\"></span> <span class=\"d3-color-ff6969ff\">+[626 - 750] Strength</span>","text":"+[626 - 750] Strength"},{"textHtml":"<span class=\"tooltip-icon-bullet\"></span> <span class=\"d3-color-ff6969ff\">+[626 - 750] Dexterity</span>","text":"+[626 - 750] Dexterity"},{"textHtml":"<span class=\"tooltip-icon-bullet\"></span> <span class=\"d3-color-ff6969ff\">+[626 - 750] Intelligence</span>","text":"+[626 - 750] Intelligence"}]}],"setItems":[]}