{"id":"Unique_Bow_007_1xx","slug":"longshot","name":"Longshot","icon":"unique_bow_007_1xx_demonhunter_male","tooltipParams":"/artisan/blacksmith/recipe/longshot","requiredLevel":20,"stackSizeMax":0,"accountBound":true,"flavorText":"Many a hero has wielded this bow through many an age, and the tales sung of it can be heard from one end of the world to the other.","flavorTextHtml":"<span class=\"d3-color-ffc7b377\">Many a hero has wielded this bow through many an age, and the tales sung of it can be heard from one end of the world to the other.                                                                                      </span>","typeName":"Legendary Bow","type":{"twoHanded":true,"id":"Bow"},"damage":"6-35 Damage\n1.40 Attacks per Second","dps":"28.7","damageHtml":"<p>6-35 <span class=\"d3-color-FF888888\">Damage</span></p>\n<p>1.40 <span class=\"d3-color-FF888888\">Attacks per Second</span></p>","color":"orange","isSeasonRequiredToDrop":false,"seasonRequiredToDrop":-1,"slots":["left-hand","right-hand","follower-left-hand","follower-right-hand"],"attributes":{"primary":[{"textHtml":"<span class=\"tooltip-icon-bullet\"></span> <span class=\"d3-color-ff6969ff\">+[11 - 13]-[14 - 17] Damage</span>","text":"+[11 - 13]-[14 - 17] Damage"},{"textHtml":"<span class=\"tooltip-icon-bullet\"></span> <span class=\"d3-color-ff6969ff\">Increases Attack Speed by [3 - 4]%</span>","text":"Increases Attack Speed by [3 - 4]%"},{"textHtml":"<span class=\"tooltip-icon-bullet\"></span> <span class=\"d3-color-ff6969ff\">Critical Hit Damage Increased by [31.0 - 35.0]% </span>","text":"Critical Hit Damage Increased by [31.0 - 35.0]%"}],"secondary":[],"other":[]},"setItems":[]}