{"id":"Wand_002","slug":"oak-wand","name":"Oak Wand","icon":"wand_002_demonhunter_male","tooltipParams":"/item/oak-wand-Wand_002","requiredLevel":6,"stackSizeMax":0,"accountBound":false,"typeName":"Wand","type":{"twoHanded":false,"id":"Wand"},"damage":"6-10 Damage\n1.40 Attacks per Second","dps":"11.2","damageHtml":"<p>6-10 <span class=\"d3-color-FF888888\">Damage</span></p>\n<p>1.40 <span class=\"d3-color-FF888888\">Attacks per Second</span></p>","color":"white","isSeasonRequiredToDrop":false,"seasonRequiredToDrop":-1,"slots":["right-hand","left-hand","follower-right-hand","follower-left-hand"],"setItems":[]}