{"id":"p43_RetroAmulet_001","slug":"optic-amulet","name":"Optic Amulet","icon":"p43_retroamulet_001_demonhunter_male","tooltipParams":"/item/optic-amulet-p43_RetroAmulet_001","requiredLevel":0,"stackSizeMax":0,"accountBound":false,"flavorText":"It seems to see what you see not...","flavorTextHtml":"<span class=\"d3-color-ffc7b377\">It seems to see what you see not...</span><br />","typeName":"Magic Amulet","type":{"twoHanded":false,"id":"Amulet"},"color":"blue","isSeasonRequiredToDrop":false,"seasonRequiredToDrop":-1,"slots":["neck","follower-neck"],"setItems":[]}