{"id":"CraftingPlan_Smith_12_Legendary_Set_Sage_X1","slug":"plan-sages-journey","name":"Plan: Sage's Journey","icon":"craftingplan_smith_12_legendary_set_sage_x1_demonhunter_male","tooltipParams":"/item/plan-sages-journey-CraftingPlan_Smith_12_Legendary_Set_Sage_X1","requiredLevel":0,"stackSizeMax":10,"accountBound":true,"typeName":"Set Blacksmith Plan","type":{"twoHanded":false,"id":"CraftingPlanLegendary_Smith"},"color":"green","description":"Teaches the Blacksmith how to craft the Legendary Set, Sage's Journey.","descriptionHtml":"<p>Teaches the Blacksmith how to craft the Legendary Set, Sage's Journey.</p>","isSeasonRequiredToDrop":false,"seasonRequiredToDrop":-1,"slots":[],"setItems":[]}