{"id":"P61_Unique_Fist_013_x1","slug":"scarbringer","name":"Scarbringer","icon":"p61_unique_fist_013_x1_demonhunter_male","tooltipParams":"/item/scarbringer-P61_Unique_Fist_013_x1","requiredLevel":30,"stackSizeMax":0,"accountBound":true,"flavorText":"Each scar left in its wake is a sin forgiven.","flavorTextHtml":"<span class=\"d3-color-ffc7b377\">Each scar left in its wake is a sin forgiven.</span>","typeName":"Legendary Fist Weapon","type":{"twoHanded":false,"id":"FistWeapon"},"damage":"16-36 Damage\n1.40 Attacks per Second","dps":"36.4","damageHtml":"<p>16-36 <span class=\"d3-color-FF888888\">Damage</span></p>\n<p>1.40 <span class=\"d3-color-FF888888\">Attacks per Second</span></p>","color":"orange","isSeasonRequiredToDrop":false,"seasonRequiredToDrop":-1,"slots":["right-hand","left-hand","follower-right-hand","follower-left-hand"],"attributes":{"primary":[{"textHtml":"<span class=\"tooltip-icon-bullet\"></span> <span class=\"d3-color-ff6969ff\">+[626 - 750] Dexterity</span>","text":"+[626 - 750] Dexterity"},{"textHtml":"<span class=\"tooltip-icon-bullet\"></span> <span class=\"d3-color-ff6969ff\">+[981 - 1199]-[1175 - 1490] Holy Damage</span>","text":"+[981 - 1199]-[1175 - 1490] Holy Damage"}],"secondary":[{"textHtml":"<span class=\"d3-color-ffff8000\"> The damage of Lashing Tail Kick is increased by <span class=\"d3-color-magic\">546%</span> to the first 7 enemies hit.</span> <span class=\"d3-color-ffff0000\">(Monk Only)</span> <span class=\"d3-color-ff9b9b9b\">[450 - 600]%</span>","text":"The damage of Lashing Tail Kick is increased by 546% to the first 7 enemies hit. (Monk Only) [450 - 600]%"}],"other":[]},"setItems":[]}