{"id":"TransmogFlail_241_003","slug":"the-spirit-of-the-zakarum","name":"The Spirit of the Zakarum","icon":"transmogflail_241_003_demonhunter_male","tooltipParams":"/item/the-spirit-of-the-zakarum-TransmogFlail_241_003","requiredLevel":1,"stackSizeMax":0,"accountBound":false,"flavorText":"“If the purity of the Zakarum runs through your veins, the spirits of the fallen will stiffen your resolve.” - Elder Crusader Drakon","flavorTextHtml":"<span class=\"d3-color-ffc7b377\">“If the purity of the Zakarum runs through your veins, the spirits of the fallen will stiffen your resolve.” - Elder Crusader Drakon</span>","typeName":"Two-Handed Flail","type":{"twoHanded":true,"id":"Flail2H"},"damage":"8-8 Damage\n1.15 Attacks per Second","dps":"9.2","damageHtml":"<p>8-8 <span class=\"d3-color-FF888888\">Damage</span></p>\n<p>1.15 <span class=\"d3-color-FF888888\">Attacks per Second</span></p>","color":"white","isSeasonRequiredToDrop":false,"seasonRequiredToDrop":-1,"slots":["right-hand","left-hand","follower-left-hand"],"setItems":[]}