{"id":"x1_FollowerItem_Enchantress_Legendary_03","slug":"vadims-surge","name":"Vadim's Surge","icon":"x1_followeritem_enchantress_legendary_03_demonhunter_male","tooltipParams":"/item/vadims-surge-x1_FollowerItem_Enchantress_Legendary_03","requiredLevel":61,"stackSizeMax":0,"accountBound":true,"flavorText":"Master Vadim found that in his later years, it took him longer to recover from each spellcasting. He created a focus that would allow him to cast much more quickly, but soon after fell prey to dementia and became quite dangerous.","flavorTextHtml":"<span class=\"d3-color-ffc7b377\">Master Vadim found that in his later years, it took him longer to recover from each spellcasting. He created a focus that would allow him to cast much more quickly, but soon after fell prey to dementia and became quite dangerous.</span>","typeName":"Legendary Enchantress Focus","type":{"twoHanded":false,"id":"EnchantressSpecial"},"color":"orange","isSeasonRequiredToDrop":false,"seasonRequiredToDrop":1,"slots":["follower-special"],"attributes":{"primary":[{"textHtml":"<span class=\"tooltip-icon-bullet\"></span> <span class=\"d3-color-ff6969ff\">+[626 - 750] Intelligence</span>","text":"+[626 - 750] Intelligence"}],"secondary":[{"textHtml":"<span class=\"d3-color-ffff8000\"><span class=\"tooltip-icon-utility\"></span> Equip on Follower: Reduce the cooldown of all Follower skills by 50%.</span>","text":"Equip on Follower: Reduce the cooldown of all Follower skills by 50%."}],"other":[]},"setItems":[]}